rng_alg-1.6.0.dist-info/licenses/LICENSE
rngalg/__init__.py
rngalg/rngalg.py
rng_alg-1.6.0.dist-info/METADATA
rng_alg-1.6.0.dist-info/WHEEL
rng_alg-1.6.0.dist-info/top_level.txt
rng_alg-1.6.0.dist-info/RECORD
