Metadata-Version: 2.4
Name: rng-alg
Version: 1.6.0
Summary: A package for random number generation algorithms like hexadecimal, pi, and advanced RNGs.
Home-page: 
Author: Nickels
Author-email: Nickels74130@outlook.fr
Classifier: Programming Language :: Python :: 3
Classifier: License :: Other/Proprietary License
Classifier: Operating System :: OS Independent
License-File: LICENSE
Dynamic: author
Dynamic: author-email
Dynamic: classifier
Dynamic: description
Dynamic: description-content-type
Dynamic: license-file
Dynamic: summary
